Metadata-Version: 2.4
Name: calico-reveal
Version: 0.2.0
Summary: A Calico plugin for a reveal.js widget
Author: Emma Delescolle
License: MIT
Project-URL: Homepage, https://calico-ssg.com
Classifier: Framework :: Django :: 5
Classifier: License :: OSI Approved :: MIT License
Requires-Dist: calico_ssg
